metadata_expander/__init__.py
metadata_expander/custom_exceptions.py
metadata_expander/sites/__init__.py
metadata_expander/sites/acm.py
metadata_expander/sites/elsevier.py
metadata_expander/sites/example.py
metadata_expander/sites/google.py
metadata_expander/sites/ieee.py
metadata_expander/sites/iospress.py
metadata_expander/sites/landing_page.py
metadata_expander/sites/springer.py
metadata_expander/sites/theiet.py
metadata_expander/sites/tib.py
metadata_expander/sites/unitrier.py
metadata_expander-0.2.4.dist-info/LICENSE
metadata_expander-0.2.4.dist-info/METADATA
metadata_expander-0.2.4.dist-info/WHEEL
metadata_expander-0.2.4.dist-info/top_level.txt
metadata_expander-0.2.4.dist-info/RECORD
