Metadata-Version: 2.1
Name: metadata-expander
Version: 0.2.4
Summary: doi search and return metadata
Home-page: https://gibraltar.chi.uni-hannover.de/literature/metadata_expander
Author: Fabian Pflug
Author-email: pflug@chi.uni-hannover.de
License: UNKNOWN
Platform: UNKNOWN
Classifier: Programming Language :: Python :: 3
Classifier: License :: OSI Approved :: MIT License
Classifier: Operating System :: OS Independent
Requires-Dist: beautifulsoup4
Requires-Dist: bibtexparser
Requires-Dist: scraping-browser (>=0.2.4)
